nrql/__init__.py
nrql/__main__.py
nrql/api.py
nrql/app.py
nrql/args_parser.py
nrql/utils.py
nrql_simple-1.3.0.dist-info/METADATA
nrql_simple-1.3.0.dist-info/WHEEL
nrql_simple-1.3.0.dist-info/entry_points.txt
nrql_simple-1.3.0.dist-info/top_level.txt
nrql_simple-1.3.0.dist-info/RECORD
