Metadata-Version: 2.1
Name: nrql-simple
Version: 1.3.0
Summary: nrql-simple is a small Python library that provides a convenient way to interact with the New Relic Insights query API. You can interact with this library programmatically or via the Command Line.
Home-page: https://github.com/anthonybloomer/nrql-simple
Author: Anthony Bloomer
Author-email: ant0@protonmail.ch
License: MIT
Platform: UNKNOWN
Classifier: Intended Audience :: Developers
Classifier: License :: OSI Approved :: MIT License
Classifier: Topic :: Software Development :: Libraries
Classifier: Programming Language :: Python
Classifier: Programming Language :: Python :: 2.7
Classifier: Programming Language :: Python :: 3
Classifier: Programming Language :: Python :: 3.3
Classifier: Programming Language :: Python :: 3.4
Classifier: Programming Language :: Python :: 3.5
Classifier: Programming Language :: Python :: 3.6
Requires-Python: >=2.7.10
Requires-Dist: requests
Requires-Dist: pygments
Requires-Dist: colorful
Requires-Dist: pandas
